num2es/num2es.py
num2es/test2.py
num2es/__init__.py
num2es-1.0.0a1.dist-info/DESCRIPTION.rst
num2es-1.0.0a1.dist-info/METADATA
num2es-1.0.0a1.dist-info/metadata.json
num2es-1.0.0a1.dist-info/RECORD
num2es-1.0.0a1.dist-info/top_level.txt
num2es-1.0.0a1.dist-info/WHEEL
